juice_segmentation/__init__.py
juice_segmentation/juice_segmentation_multi_cmd.py
juice_segmentation/spice_segmentation_cmd.py
juice_segmentation/commons/__init__.py
juice_segmentation/commons/authentication.py
juice_segmentation/commons/mission_phases.py
juice_segmentation/commons/mission_timeline_event_file_handler.py
juice_segmentation/commons/rest_api.py
juice_segmentation/commons/segment_definition_handler.py
juice_segmentation/commons/segment_handler.py
juice_segmentation/commons/sht_rest_api.py
juice_segmentation/report/__init__.py
juice_segmentation/report/metrics.py
juice_segmentation/report/rst_report.py
juice_segmentation/report/segmentation_report.py
juice_segmentation/report/templates/custom-reference.docx
juice_segmentation/report/templates/default_rst2pdf.style
juice_segmentation/segmentation/__init__.py
juice_segmentation/segmentation/segmentation.py
juice_segmentation/segmentation_multi/__init__.py
juice_segmentation/segmentation_multi/generic_schedulling.py
juice_segmentation/segmentation_multi/op_nav_schedulling.py
juice_segmentation/segmentation_multi/partitions.py
juice_segmentation/segmentation_multi/segment_instance.py
juice_segmentation/segmentation_multi/segmentation.py
juice_segmentation/spice_segmentation/__init__.py
juice_segmentation/spice_segmentation/spice_segmentation.py
juice_segmentation/spice_segmentation/wg_segment_handler.py
juice_segmentation/utest/__init__.py
juice_segmentation/utest/utest_metrics.py
juice_segmentation/utest/utest_wg_seg_basic.py
juice_segmentation/utest/utest_wg_segment_handler.py
juice_segmentation/utest/utest_wg_segment_prime_mapping.py
juice_segmentation/utest/utest_wg_utils.py
juice_segmentation/utest/data/OPPORTUNITY_PRIME_correspondance_test.csv
juice_segmentation/utest/data/mission_timeline_event_file_5_0_PE_FB.csv
juice_segmentation/utest/fd_events/__init__.py
juice_segmentation/utest/fd_events/todo_utest_fd_segment.py
juice_segmentation/wg/__init__.py
juice_segmentation/wg/wg_calib_handler.py
juice_segmentation-0.6.10.dist-info/METADATA
juice_segmentation-0.6.10.dist-info/WHEEL
juice_segmentation-0.6.10.dist-info/entry_points.txt
juice_segmentation-0.6.10.dist-info/top_level.txt
juice_segmentation-0.6.10.dist-info/RECORD
