Metadata-Version: 2.1
Name: juice-segmentation
Version: 0.6.10
Summary: Python package for merging/cutting segments according given rules
Home-page: https://juigitlab.esac.esa.int/core-system/uplink/juice_segmentation
Author: JUICE SOC team
Author-email: juice_soc@cosmos.esa.int
Keywords: esa,science,planetary,space,planning,merging,cutting,rules
Classifier: Development Status :: 3 - Alpha
Classifier: Intended Audience :: Science/Research
Classifier: Topic :: Scientific/Engineering :: Astronomy
Classifier: Programming Language :: Python :: 3.7
Requires-Dist: tabulate >=0.9.0
Requires-Dist: requests >=2.28.2
Requires-Dist: rst2html5 >=2.0
Requires-Dist: esac-juice-pyutils >=0.3.1
